Metadata-Version: 1.1
Name: explode-struct-schema
Version: 0.1.1
Summary: To explode the nested json in key value pair to read the dynamodb columns directly from spark dataframe
Home-page: UNKNOWN
Author: Deep Lakkad
Author-email: deeplakkad7@gmail.com
License: MIT
Keywords: explode,dynamodb,json,struct
Platform: UNKNOWN
Classifier: Development Status :: 5 - Production/Stable
Classifier: Intended Audience :: Education
Classifier: Operating System :: Microsoft :: Windows :: Windows 10
Classifier: License :: OSI Approved :: MIT License
Classifier: Programming Language :: Python :: 3
